flask_rq/__init__.py
flask_rq/_cli.py
flask_rq/_extension.py
flask_rq/_job_class.py
flask_rq/_job_wrapper.py
flask_rq/_make.py
flask_rq/_old.py
flask_rq/py.typed
flask_rq-0.3.3.dist-info/licenses/LICENSE.txt
flask_rq-0.3.3.dist-info/WHEEL
flask_rq-0.3.3.dist-info/METADATA
flask_rq-0.3.3.dist-info/RECORD
