Metadata-Version: 2.4
Name: Flask-RQ
Version: 0.3.3
Summary: RQ (Redis Queue) integration for Flask and Quart applications.
Maintainer-email: Pallets Ecosystem <contact@palletsprojects.com>
Requires-Python: >=3.9
License-Expression: MIT
License-File: LICENSE.txt
Requires-Dist: flask[async]>=3.0
Requires-Dist: rq>=2.0
Requires-Dist: typing-extensions>=4.12
Requires-Dist: quart>=0.20 ; extra == "quart"
Project-URL: Changes, https://flask-rq.readthedocs.io/page/changes/
Project-URL: Chat, https://discord.gg/pallets
Project-URL: Documentation, https://flask-rq.readthedocs.io
Project-URL: Donate, https://palletsprojects.com/donate
Project-URL: Source, https://github.com/pallets-eco/flask-rq/
Provides-Extra: quart
